Metadata-Version: 2.1
Name: PV-Hawk-Viewer
Version: 1.1.0
Summary: Viewer for PV Hawk datasets.
Home-page: https://github.com/LukasBommes/PV-Hawk-Viewer
Maintainer: Lukas Bommes
License: MIT
Keywords: PV Hawk,Photovoltaic,Defects,Mapping,PV Plant,Drone,Thermography
Platform: ALL
Classifier: Operating System :: OS Independent
Classifier: Programming Language :: Python :: 3
Requires-Python: >=3.8, <4
License-File: LICENSE
Requires-Dist: numpy (<2,>=1.19.1)
Requires-Dist: pandas (<2,>=1.1.2)
Requires-Dist: matplotlib (<4,>=3.5.0rc1)
Requires-Dist: scikit-learn (<2,>=0.23.1)
Requires-Dist: opencv-python (<5,>=4.2.0.34)
Requires-Dist: networkx (<3,>=2.4)
Requires-Dist: PySide6 (<6.2.4,>=6.2.1)
Requires-Dist: pyproj (<4,>=3.1.0)
Requires-Dist: shapely (<2,>=1.7.1)
